{"chunk_definitions":[{"row":33,"row_count":1,"visible":true,"expansion_state":0,"options":{"engine":"css","echo":false,"label":"unnamed-chunk-2"},"document_id":"0981F25A","chunk_id":"cngp94iljd6sy","chunk_label":"unnamed-chunk-1"},{"row":37,"row_count":1,"visible":true,"expansion_state":0,"options":{"engine":"r","include":false,"label":"unnamed-chunk-3"},"document_id":"0981F25A","chunk_id":"cw2180veyn0dp","chunk_label":"unnamed-chunk-2"},{"row":58,"row_count":1,"visible":true,"expansion_state":0,"options":{"engine":"r","label":"setup","include":false},"document_id":"0981F25A","chunk_id":"csetup_chunk","chunk_label":"setup"},{"row":65,"row_count":1,"visible":true,"expansion_state":0,"options":{"engine":"r","label":"load data","include":false},"document_id":"0981F25A","chunk_id":"cttogfn0yhkw0","chunk_label":"load data"},{"row":132,"row_count":1,"visible":true,"expansion_state":0,"options":{"engine":"r","echo":false,"label":"unnamed-chunk-4"},"document_id":"0981F25A","chunk_id":"cbdzex3tmmqr2","chunk_label":"unnamed-chunk-3"},{"row":150,"row_count":1,"visible":true,"expansion_state":0,"options":{"engine":"r","echo":false,"fig.height":6,"fig.width":7,"label":"unnamed-chunk-5"},"document_id":"0981F25A","chunk_id":"cfw6xi1r0w1rb","chunk_label":"unnamed-chunk-4"}],"doc_write_time":1615317091,"working_dir":null,"default_chunk_options":{}}